{
	"pages": [
		{
			"path": "pages/index/agenda"
		},
		{
			"path": "pages/index/home"
		},
		{
			"path": "pages/index/wonderful-life"
		},
		{
			"path": "pages/index/exhibition-style"
		},
		{
			"path": "pages/index/myself"
		},
		{
			"path": "pages/components/video/video-detail",
			"style": {
				"navigationBarTitleText": "",
				"enablePullDownRefresh": false
			}
		},
		{
			"path": "pages/index/news-msg",
			"style": {
				"navigationBarTitleText": "",
				"enablePullDownRefresh": false
			}
		},
		{
			"path": "pages/components/article/article-item",
			"style": {
				"navigationBarTitleText": "",
				"enablePullDownRefresh": false
			}
		},
		{
			"path": "pages/index/article-msg",
			"style": {
				"navigationBarTitleText": "",
				"enablePullDownRefresh": false
			}
		},
		{
			"path": "pages/components/video/video-test",
			"style": {
				"navigationBarTitleText": "",
				"enablePullDownRefresh": false
			}
		},
		{
			"path": "pages/index/test",
			"style": {
				"navigationBarTitleText": "",
				"enablePullDownRefresh": false
			}
		},
		{
			"path": "pages/index/my-subscription",
			"style": {
				"navigationBarTitleText": "",
				"enablePullDownRefresh": false
			}
		},
		{
			"path" : "pages/components/wonderful-life-item/wonderful-life-item",
			"style" : 
			{
				"navigationBarTitleText" : "",
				"enablePullDownRefresh" : false
			}
		},
		{
			"path" : "pages/index/score-store",
			"style" : 
			{
				"navigationBarTitleText" : "",
				"enablePullDownRefresh" : false
			}
		},
		{
			"path" : "pages/components/store/store-item",
			"style" : 
			{
				"navigationBarTitleText" : "",
				"enablePullDownRefresh" : false
			}
		},
		{
			"path" : "pages/index/get-award",
			"style" : 
			{
				"navigationBarTitleText" : "",
				"enablePullDownRefresh" : false
			}
		}
	],
	"condition": {
		"current": 0,
		"list": [{
			"name": "大会议程详情页",
			"path": "pages/components/video/video-detail"
			// "query": "name=ttt"
		}]
	},
	// 菜单
	// "tabBar": {
	// 	"color": "#8F8F8F",
	// 	"selectedColor": "#4793DC",
	// 	"borderStyle": "black",
	// 	"backgroundColor": "#ffffff",
	// 	"list": [
	// 		{
	// 			"text": "首页",
	// 			"pagePath": "pages/index/home",
	// 			"iconPath": "static/tab/home.png",
	// 			"selectedIconPath": "static/tab/home-active.png"
	// 		},
	// 		{
	// 			"text": "精彩生活",
	// 			"pagePath": "pages/index/wonderful-life",
	// 			"iconPath": "static/tab/wonderful-life.png",
	// 			"selectedIconPath": "static/tab/wonderful-life-active.png"
	// 		},
	// 		{
	// 			"text": "大会议程",
	// 			"pagePath": "pages/index/agenda",
	// 			"iconPath": "static/tab/agenda.png",
	// 			"selectedIconPath": "static/tab/agenda-active.png"
	// 		},
	// 		{
	// 			"text": "展商风采",
	// 			"pagePath": "pages/index/exhibition-style",
	// 			"iconPath": "static/tab/exhibtion-style.png",
	// 			"selectedIconPath": "static/tab/exhibtion-style-active.png"
	// 		},
	// 		{
	// 			"text": "我的",
	// 			"pagePath": "pages/index/myself",
	// 			"iconPath": "static/tab/myself.png",
	// 			"selectedIconPath": "static/tab/myself-active.png"
	// 		}
	// 	],
	// 全局样式设计
	"globalStyle": {
		"navigationBarTextStyle": "black",
		"navigationBarTitleText": "uni-app-test",
		"navigationBarBackgroundColor": "#F8F8F8",
		"backgroundColor": "#F8F8F8",
		"enablePullDownRefresh": true,
		"backgroundTextStyle": "dark"
	},

	"uniIdRouter": {

	},
	"easycom": {
		"autoscan": true,
		"custom": {
			"l-swiper": "/uni-modules/l-swiper/components/l-swiper/l-swiper.vue"
		}
	}
}